prodigyteams/__init__.py
prodigyteams/about.py
prodigyteams/cluster.py
prodigyteams/gcp.py
prodigyteams/main.py
prodigyteams/packages.py
prodigyteams/projects.py
prodigyteams/recipes.py
prodigyteams/sources.py
prodigyteams/spinner.py
prodigyteams/tasks.py
prodigyteams/utils.py
tests/__init__.py
tests/conftest.py
tests/test_cluster.py
tests/test_local_cache.py
tests/test_main.py
tests/test_packages.py
tests/test_projects.py
tests/test_sources.py
tests/test_tasks.py
mort_jams_cli-0.0.11.dist-info/LICENSE
mort_jams_cli-0.0.11.dist-info/METADATA
mort_jams_cli-0.0.11.dist-info/WHEEL
mort_jams_cli-0.0.11.dist-info/entry_points.txt
mort_jams_cli-0.0.11.dist-info/top_level.txt
mort_jams_cli-0.0.11.dist-info/RECORD
